{
  "Sizes8": 8,
  "ColorBasePrimary": "#df2121",
  "ColorBaseSecondary": "#0032eb",
  "ColorBorderDefault": "#d9d9d9",
  "ColorBorderLight": "#f2f2f2",
  "ColorBorderNeutral": "#959595",
  "ColorBorderActive": "#959595",
  "ColorBorderFocus": "#959595",
  "ColorBorderSuccess": "#00aa13",
  "ColorBorderError": "#fd3916",
  "ColorBorderStrong": "#959595",
  "ColorBrandPrimary": "#00aa13",
  "ColorBrandSecondary": "#003da5",
  "ColorBrandTertiary": "#fedb00",
  "ColorBrandWhite": "#ffffff",
  "ColorBrandBlack": "#242424",
  "ColorNeutralGreyPaler": "#f9f9f9",
  "ColorNeutralGreyStrong": "#959595",
  "ColorNeutralGreyPale": "#f2f2f2",
  "ColorNeutralNeutralPale": "#f2f2f2",
  "ColorNeutralNeutralStrong": "#959595",
  "ColorNeutralBlack": "#211a2b",
  "ColorUiActive": "#959595",
  "ColorUiFocus": "#959595",
  "ColorUiInfoStrong": "#959595",
  "ColorUiInfoPale": "#f2f2f2",
  "ColorUiDangerStrong": "#ff5400",
  "ColorUiDangerPale": "#fff9e4",
  "ColorUiErrorStrong": "#fd3916",
  "ColorUiErrorPale": "#feede9",
  "ColorUiSuccessStrong": "#00aa13",
  "ColorUiSuccessPale": "#e2f8ed",
  "ColorLinkPrimary": "#003da5",
  "ColorLinkSecondary": "#003da5",
  "ColorLinkNeutral": "#211a2b",
  "ColorLinkList": "#211a2b",
  "ColorButtonPrimaryBackground": "#ff5400",
  "ColorButtonPrimaryText": "#ffffff",
  "ColorButtonSecondaryBackground": "#ff5400",
  "ColorButtonSecondaryText": "#ff5400",
  "ColorButtonTertiaryBackground": "#f3f3f3",
  "ColorButtonTertiaryText": "#111111",
  "ColorButtonTextColor": "#ff5400",
  "ColorTextBlack": "#211a2b",
  "ColorTextWhite": "#ffffff",
  "ColorTextPrice": "#211a2b",
  "ColorTextCta": "#00aa13",
  "ColorTextPale": "#d9d9d9",
  "ColorTextDefault": "#757575",
  "ColorTextError": "#e7314c",
  "ColorTextSuccess": "#00aa13",
  "ColorTextDanger": "#ff5400",
  "ColorTextIncentivePrice": "#ed3325",
  "ColorTextIncentiveCta": "#ed3325",
  "ColorTextNeutralPale": "#d9d9d9",
  "ColorTextNeutralGreyDefault": "#7f7f7f",
  "ColorTextFeedbackError": "#ed3325",
  "ColorTextFeedbackSuccess": "#0fbf26",
  "ColorTextFeedbackDanger": "#fe8f2f",
  "ColorTextGrey": "#959595",
  "ColorTextGreyPale": "#d9d9d9",
  "ColorSettingsPlaceholder": "#04316a",
  "ColorSettingsOverlay": "#111111",
  "ColorSettingsOverigLoadingColor": "#00aa13",
  "ColorSettingsBannerTextCta": "#00aa13",
  "ColorSettingsBannerHighlight": "#00aa13",
  "ColorSettingsBannerBackground": "#ecf3de",
  "ColorSettingsBannerBackgroundCta": "#00aa13",
  "ColorSettingsBannerBannerGenreBackground": "#00aa13",
  "ColorSettingsBannerSecondaryText": "#00aa13",
  "ColorSettingsBannerSecondaryBackground": "#00aa13",
  "ColorSettingsBannerPrimaryBackground": "#00aa13",
  "ColorSettingsBannerPrimaryText": "#00aa13",
  "ColorSettingsFormCheckboxDisabledBackground": "#f3f3f3",
  "ColorSettingsFormCheckboxCheckedColor": "#959595",
  "ColorSettingsFormCheckboxHoverText": "#ffffff",
  "ColorSettingsFormRadioTextActive": "#00aa13",
  "ColorSettingsFormInputBorder": "#d9d9d9",
  "ColorSettingsIconDefault": "#211a2b",
  "ColorSettingsIconRatingRatingActive": "#fdd416",
  "ColorSettingsIconRatingRatingInactive": "#d9d9d9",
  "ColorSettingsIconRatingActive": "#fedb00",
  "ColorSettingsIconRatingInactive": "#d9d9d9",
  "ColorSettingsMastheadBackground": "#ffffff",
  "ColorSettingsMastheadTextAction": "#211a2b",
  "ColorSettingsMastheadBackgroundActionHover": "#d9d9d9",
  "ColorSettingsMastheadBackgroundActionHighlighted": "#d9d9d9",
  "ColorSettingsMastheadTextActionHighlighted": "#211a2b",
  "ColorSettingsNavigationBarBackground": "#00aa13",
  "ColorSettingsNavigationBarText": "#ffffff",
  "ColorSettingsNavigationBarTextCta": "#ffffff",
  "ColorSettingsNavigationBarTextActive": "#ffffff",
  "ColorSettingsUspBarBackground": "#ffffff",
  "ColorSettingsUspBarText": "#211a2b",
  "ColorSettingsUspBarIconCheck": "#00aa13",
  "ColorSettingsUspBarBorder": "#f2f2f2",
  "ColorSettingsUspBarIcon": "#211a2b",
  "ColorSettingsNavigationText": "#211a2b",
  "ColorSettingsNavigationTextActive": "#211a2b",
  "ColorSettingsNavigationTextHover": "#211a2b",
  "ColorSettingsNavigationTextDisabled": "#959595",
  "ColorSettingsNavigationBackgroundHover": "#f9f9f9",
  "ColorSettingsNavigationBackgroundActive": "#00aa13",
  "ColorSettingsNavigationBackground": "#ffffff",
  "ColorSettingsNavigationBackgroundDisabled": "#ffffff",
  "ColorSettingsButtonPrimaryBackground": "#ed3325",
  "ColorSettingsButtonPrimaryText": "#ffffff",
  "ColorSettingsButtonSecondaryBackground": "#e7f3ff",
  "ColorSettingsButtonSecondaryText": "#242424",
  "ColorSettingsButtonTertiaryBackground": "#e7f3ff",
  "ColorSettingsButtonTertiaryText": "#242424",
  "ColorSettingsButtonTextColor": "#ed3325",
  "ColorSettingsBadgeTextBackground": "#003da5",
  "ColorSettingsBadgeTextText": "#ffffff",
  "ColorSettingsBadgePriceBackground": "#ed3325",
  "ColorSettingsBadgePriceText": "#ffffff",
  "ColorSettingsBadgeTagBackground": "#00aa13",
  "ColorSettingsBadgeTagText": "#ffffff",
  "ColorSettingsBadgeBlockBackground": "#f3f3f3",
  "ColorSettingsBadgeBlockText": "#211a2b",
  "ColorSettingsBadgeBlockHighlight": "#00aa13",
  "ColorSettingsBadgeBlockButton": "#00aa13",
  "ColorSettingsBadgeSecondaryBackground": "#00aa13",
  "ColorSettingsBadgeSecondaryText": "#ffffff",
  "ColorSettingsBadgePrimaryBackground": "#fedb00",
  "ColorSettingsBadgePrimaryText": "#ffffff",
  "ColorBadgeTextBackground": "#fdd416",
  "ColorBadgeTextText": "#211a2b",
  "ColorBadgePriceBackground": "#ed3325",
  "ColorBadgePriceText": "#ffffff",
  "ColorBadgeTagBackground": "#fdd416",
  "ColorBadgeTagText": "#4153a0",
  "ColorBadgeBlockBackground": "#f2f2f2",
  "ColorBadgeBlockText": "#211a2b",
  "ColorBadgeBlockHighlight": "#e7314c",
  "ColorBadgeBlockButton": "#e7314c",
  "ColorBadgeSecondaryBackground": "#fdd416",
  "ColorBadgeSecondaryText": "#4153a0",
  "ColorBadgePrimaryBackground": "#e7314c",
  "ColorBadgePrimaryText": "#ffffff",
  "ColorThemeDefaultPale": "#edf2e0",
  "ColorThemeDefaultStrong": "#d8e7b9",
  "ColorThemeOrangePale": "#edf2e0",
  "ColorThemeOrangeStrong": "#d8e7b9",
  "ColorThemeYellowPale": "#edf2e0",
  "ColorThemeYellowStrong": "#d8e7b9",
  "ColorThemeGreenPale": "#edf2e0",
  "ColorThemeGreenStrong": "#d8e7b9",
  "ColorThemeBluePale": "#edf2e0",
  "ColorThemeBlueStrong": "#d8e7b9",
  "ColorThemePinkPale": "#edf2e0",
  "ColorThemePinkStrong": "#d8e7b9",
  "ColorThemeRedPale": "#edf2e0",
  "ColorThemeRedStrong": "#d8e7b9",
  "ColorThemeGreyPale": "#edf2e0",
  "ColorThemeGreyStrong": "#d8e7b9",
  "ColorThemeGreyBluePale": "#edf2e0",
  "ColorThemeGreyBlueStrong": "#d8e7b9",
  "ColorThemePurplePale": "#edf2e0",
  "ColorThemePurpleDark": "#d8e7b9"
}